test_ai/__init__.py
test_ai/test_ai.py
test_ai_python-0.0.12.dist-info/LICENSE
test_ai_python-0.0.12.dist-info/METADATA
test_ai_python-0.0.12.dist-info/WHEEL
test_ai_python-0.0.12.dist-info/top_level.txt
test_ai_python-0.0.12.dist-info/RECORD
